
{
    "region" : "ap-south-1",
    "profile" : "lambda-authorizer-profile",
    "configuration" : "Release",
    "framework"     : "net6.0",
    "function-name" : "generate-token",
    "function-description" : "",
    "package-type"         : "Zip",
    "function-handler"     : "AWS.Lambda.Authorizer.Example.Authentication::AWS.Lambda.Authorizer.Example.Authentication.Function::GenerateTokenAsync",
    "function-memory-size" : 256,
    "function-timeout"     : 30,
    "function-runtime"     : "dotnet6",
    "function-architecture" : "x86_64",
    "tracing-mode"          : "PassThrough",
    "environment-variables" : "",
    "image-tag"             : "",
    "function-role"         : "arn:aws:iam::567921601443:role/lambda_exec_generate-token",
    "function-subnets"      : "",
    "function-security-groups" : ""
}